supervisor_console/__init__.py
supervisor_console/__main__.py
supervisor_console/console.py
supervisor_console/events.py
supervisor_console-0.5.2.dist-info/METADATA
supervisor_console-0.5.2.dist-info/WHEEL
supervisor_console-0.5.2.dist-info/entry_points.txt
supervisor_console-0.5.2.dist-info/top_level.txt
supervisor_console-0.5.2.dist-info/RECORD
