Metadata-Version: 2.1
Name: supervisor-console
Version: 0.5.2
Summary: UNKNOWN
Home-page: https://github.com/carstencodes/supervisor-console
Author: Carsten Igel
Author-email: cig@bite-that-bit.de
License: BSD-3-Clause
Platform: UNKNOWN
Classifier: Development Status :: 4 - Beta
Classifier: Environment :: Console
Classifier: License :: OSI Approved :: BSD License
Classifier: Natural Language :: English
Classifier: Operating System :: POSIX :: Linux
Classifier: Programming Language :: Python :: 3.6
Classifier: Programming Language :: Python :: 3.7
Classifier: Programming Language :: Python :: 3.8
Classifier: Topic :: Internet :: Log Analysis
Classifier: Topic :: System
Classifier: Topic :: System :: Boot
Classifier: Topic :: System :: Boot :: Init
Classifier: Topic :: System :: Logging
Classifier: Typing :: Typed
Requires-Dist: supervisor (>=4.0)
